Workbook
Name Ano: Planilha1!$D$19
Name Investimento_Mensal: Planilha1!$D$18
Name Rendimento_Carteira: Planilha1!$D$14
Name salario: Planilha1!$D$13
Name Salário: Planilha1!$D$13
Name sugestao_investimento: Planilha1!$D$15
Name Taxa_Rendimento_Mensal: Planilha1!$D$20
Name total_acumulado: Planilha1!$D$21

Sheet Planilha1
B12: CONFIGURAÇÕES
B13: Salário | D13: 4200
B14: Rendimento Carteira | D14: 0.009
B15: Sugestão de investimento(30%) | D15: =D13*30% -> 1260
B17: INVESTIMENTO MENSAL
B18: Quanto investir por mês? | D18: 1260
B19: Por Quantos anos? | D19: 10
B20: Taxa de rendimento mensal? | D20: 0.01079
B21: Patrimônio acumulado? | D21: =FV(Taxa_Rendimento_Mensal,Ano*12,Investimento_Mensal*-1) -> 306538.11
B22: Dividendo Mensais? | D22: =D21*1% -> 3065.3811
B24: OUTROS CENÁRIOS DE INVESTIMENTO | D24: REDIMENTO MENSAL
A25: 2 | B25: Quanto em 2 anos? | C25: =FV($D$20,$A25*12,$D$18*-1) -> 34306.81 | D25: =C25*Rendimento_Carteira -> 308.76129
A26: 5 | B26: Quanto em 5 anos? | C26: =FV($D$20,$A26*12,$D$18*-1) -> 105558.91 | D26: =C26*$D$14 -> 950.0302
A27: 10 | B27: Quanto em 10 anos? | C27: =FV($D$20,$A27*12,$D$18*-1) -> 306538.11 | D27: =C27*$D$14 -> 2758.843
A28: 20 | B28: Quanto em 20 anos? | C28: =FV($D$20,$A28*12,$D$18*-1) -> 1417750 | D28: =C28*$D$14 -> 12759.75
A29: 30 | B29: Quanto em 30 anos? | C29: =FV($D$20,$A29*12,$D$18*-1) -> 5445933.8 | D29: =C29*$D$14 -> 49013.404
B31: SIMULE SEUS INVESTIMENTOS DE ACORDO COM O SEU PERFIL
B32: SELECIONE SEU PERFIL COMO INVESTIDOR | C32: AGRESSIVO
B33: VALOR A SER INVESTIDO POR MÊS | C33: =Investimento_Mensal -> 1260
B35: TIPO DE FIIs | C35: PERCENTUAL SUGERIDO | D35: VALORES
B36: PAPEL | C36: =VLOOKUP($C$32&"-"&B36,'Tipos de investimentos'!$A$3:$D$20,4,FALSE) -> 0.5 | D36: =$C$33*C36 -> 630
B37: TIJOLO | C37: =VLOOKUP($C$32&"-"&B37,'Tipos de investimentos'!$A$3:$D$20,4,FALSE) -> 0.1 | D37: =$C$33*C37 -> 126
B38: HÍBRIDOS | C38: =VLOOKUP($C$32&"-"&B38,'Tipos de investimentos'!$A$3:$D$20,4,FALSE) -> 0.05 | D38: =$C$33*C38 -> 63
B39: FOFs | C39: =VLOOKUP($C$32&"-"&B39,'Tipos de investimentos'!$A$3:$D$20,4,FALSE) -> 0.05 | D39: =$C$33*C39 -> 63
B40: DESENVOLVIMENTO | C40: =VLOOKUP($C$32&"-"&B40,'Tipos de investimentos'!$A$3:$D$20,4,FALSE) -> 0.2 | D40: =$C$33*C40 -> 252
B41: HOTELARIAS | C41: =VLOOKUP($C$32&"-"&B41,'Tipos de investimentos'!$A$3:$D$20,4,FALSE) -> 0.1 | D41: =$C$33*C41 -> 126
D42: =SUM(D36:D41) -> 1260

Sheet Tipos de investimentos
A2: CHAVE COMERCIAL | B2: PERFIL | C2: TIPO DE FII | D2: PERCENTUAL SUGERIDO
A3: =B3&"-"&C3 -> CONSERVADOR-PAPEL | B3: CONSERVADOR | C3: PAPEL | D3: 0.3
A4: =B4&"-"&C4 -> CONSERVADOR-TIJOLO | B4: CONSERVADOR | C4: TIJOLO | D4: 0.5
A5: =B5&"-"&C5 -> CONSERVADOR-HÍBRIDOS | B5: CONSERVADOR | C5: HÍBRIDOS | D5: 0.1
A6: =B6&"-"&C6 -> CONSERVADOR-FOFs | B6: CONSERVADOR | C6: FOFs | D6: 0.1
A7: =B7&"-"&C7 -> CONSERVADOR-DESENVOLVIMENTO | B7: CONSERVADOR | C7: DESENVOLVIMENTO | D7: 0
A8: =B8&"-"&C8 -> CONSERVADOR-HOTELARIAS | B8: CONSERVADOR | C8: HOTELARIAS | D8: 0
A9: =B9&"-"&C9 -> MODERADO-PAPEL | B9: MODERADO | C9: PAPEL | D9: 0.32
A10: =B10&"-"&C10 -> MODERADO-TIJOLO | B10: MODERADO | C10: TIJOLO | D10: 0.35
A11: =B11&"-"&C11 -> MODERADO-HÍBRIDOS | B11: MODERADO | C11: HÍBRIDOS | D11: 0.08
A12: =B12&"-"&C12 -> MODERADO-FOFs | B12: MODERADO | C12: FOFs | D12: 0.1
A13: =B13&"-"&C13 -> MODERADO-DESENVOLVIMENTO | B13: MODERADO | C13: DESENVOLVIMENTO | D13: 0.1
A14: =B14&"-"&C14 -> MODERADO-HOTELARIAS | B14: MODERADO | C14: HOTELARIAS | D14: 0.1
... A20: =B20&"-"&C20 -> AGRESSIVO-HOTELARIAS | B20: AGRESSIVO | C20: HOTELARIAS | D20: 0.1
